channels_presence2/__init__.py
channels_presence2/core.py
channels_presence2/exceptions.py
django_channels_presence2-0.0.4a0.dist-info/DESCRIPTION.rst
django_channels_presence2-0.0.4a0.dist-info/METADATA
django_channels_presence2-0.0.4a0.dist-info/RECORD
django_channels_presence2-0.0.4a0.dist-info/WHEEL
django_channels_presence2-0.0.4a0.dist-info/metadata.json
django_channels_presence2-0.0.4a0.dist-info/top_level.txt
