Metadata-Version: 2.0
Name: django-channels-presence2
Version: 0.0.4a0
Summary: Simple presence boilerplate for django-channels 2 and channel redis backend.
Home-page: https://github.com/acrius/django-channels-presence2
Author: acrius
Author-email: acrius@mail.ru
License: MIT
Platform: UNKNOWN
